architest
