Metadata-Version: 1.1
Name: architest
Version: 0.1.6
Summary: Architest allows you to check your project's structure conformity to initial architecture
Home-page: https://github.com/VASemenov/architest
Author: Vladimir Semenov
Author-email: subatiq@gmail.com
License: MIT
Download-URL: https://github.com/VASemenov/architest/archive/refs/tags/0.1.6.tar.gz
Keywords: architest,static,test,architecture,design
Platform: UNKNOWN
Classifier: Development Status :: 3 - Alpha
Classifier: Intended Audience :: Developers
Classifier: Topic :: Software Development :: Testing
Classifier: License :: OSI Approved :: MIT License
Classifier: Programming Language :: Python :: 3.9
